CONSTANTS.py
mvtsdatatoolkit/__init__.py
mvtsdatatoolkit/configs/__init__.py
mvtsdatatoolkit/configs/config_reader.py
mvtsdatatoolkit/configs/datasets_configs.yml
mvtsdatatoolkit/configs/demo_configs.yml
mvtsdatatoolkit/configs/test_configs.yml
mvtsdatatoolkit/data/__init__.py
mvtsdatatoolkit/data/data_retriever.py
mvtsdatatoolkit/data_analysis/__init__.py
mvtsdatatoolkit/data_analysis/extracted_features_analysis.py
mvtsdatatoolkit/data_analysis/mvts_data_analysis.py
mvtsdatatoolkit/features/__init__.py
mvtsdatatoolkit/features/extractor_utils.py
mvtsdatatoolkit/features/feature_collection.py
mvtsdatatoolkit/features/feature_extractor.py
mvtsdatatoolkit/normalizing/__init__.py
mvtsdatatoolkit/normalizing/normalizer.py
mvtsdatatoolkit/sampling/__init__.py
mvtsdatatoolkit/sampling/input_validator.py
mvtsdatatoolkit/sampling/sampler.py
mvtsdatatoolkit/utils/__init__.py
mvtsdatatoolkit/utils/meta_data_getter.py
mvtsdatatoolkit/utils/mvts_cleaner.py
mvtsdatatoolkit/visualizations/__init__.py
mvtsdatatoolkit/visualizations/stat_visualizer.py
mvtsdatatoolkit-0.2.6.dist-info/LICENCE.txt
mvtsdatatoolkit-0.2.6.dist-info/METADATA
mvtsdatatoolkit-0.2.6.dist-info/WHEEL
mvtsdatatoolkit-0.2.6.dist-info/top_level.txt
mvtsdatatoolkit-0.2.6.dist-info/RECORD
