Metadata-Version: 2.1
Name: mvtsdatatoolkit
Version: 0.2.6
Summary: A Toolkit for Multivariate Time Series Data
Home-page: https://bitbucket.org/gsudmlab/mvtsdata_toolkit/src/master
Author: Azim Ahmadzadeh, Kankana Sinha
Author-email: aahmadzadeh1@cs.gsu.edu
Maintainer: Azim Ahmadzadeh
Maintainer-email: aahmadzadeh1@cs.gsu.edu
License: MIT
Project-URL: Documentation, http://dmlab.cs.gsu.edu/docs/mvtsdata_toolkit/
Project-URL: Source, https://bitbucket.org/gsudmlab/mvtsdata_toolkit/src/master
Keywords: multivariate,time series,mvts,imbalance,sampling,features
Platform: UNKNOWN
Classifier: License :: OSI Approved :: MIT License
Classifier: Programming Language :: Python :: 3
Classifier: Intended Audience :: Science/Research
Classifier: Intended Audience :: Developers
Classifier: Topic :: Scientific/Engineering :: Information Analysis
Classifier: Development Status :: 4 - Beta
Classifier: License :: OSI Approved :: MIT License
Requires-Dist: pandas (==0.24.2)
Requires-Dist: scipy (==1.3.0)
Requires-Dist: tdigest (==0.5.2.2)
Requires-Dist: seaborn (==0.9.0)
Requires-Dist: scikit-learn (==0.21.2)
Requires-Dist: matplotlib (==3.1.0)
Requires-Dist: hurry.filesize (==0.9)
Requires-Dist: PyYAML (==5.1.2)
Requires-Dist: tqdm (==4.36.1)
Requires-Dist: zipp (==0.6.0)
Requires-Dist: urllib3 (==1.24.3)
Requires-Dist: notebook (==6.0.1)
